tests/__init__.py
tests/login_page_test.py
umdriver/__init__.py
umdriver/driver.py
umdriver/exceptions.py
umdriver/utils.py
umdriver/pages/__init__.py
umdriver/pages/login_page.py
umdriver-0.0.4.dist-info/METADATA
umdriver-0.0.4.dist-info/WHEEL
umdriver-0.0.4.dist-info/top_level.txt
umdriver-0.0.4.dist-info/RECORD
